django_qc/__init__.py
django_qc/core.py
django_qc/settings.py
django_qc-1.0.1.dist-info/LICENSE
django_qc-1.0.1.dist-info/WHEEL
django_qc-1.0.1.dist-info/METADATA
django_qc-1.0.1.dist-info/RECORD
